convertext/__init__.py
convertext/__main__.py
convertext/cli.py
convertext/config.py
convertext/converters/__init__.py
convertext/converters/apple/__init__.py
convertext/converters/base.py
convertext/converters/comics/__init__.py
convertext/converters/documents/__init__.py
convertext/converters/documents/docx.py
convertext/converters/documents/html.py
convertext/converters/documents/markdown.py
convertext/converters/documents/odt.py
convertext/converters/documents/pdf.py
convertext/converters/documents/pdf_to_epub.py
convertext/converters/documents/rtf.py
convertext/converters/documents/to_docx.py
convertext/converters/documents/to_pdf.py
convertext/converters/documents/to_rtf.py
convertext/converters/documents/txt.py
convertext/converters/ebooks/__init__.py
convertext/converters/ebooks/epub.py
convertext/converters/ebooks/fb2.py
convertext/converters/ebooks/mobi.py
convertext/converters/loader.py
convertext/converters/mixins.py
convertext/converters/utils.py
convertext/core.py
convertext/exceptions.py
convertext/registry.py
convertext/templates/default_config.yaml
convertext/utils/__init__.py
convertext-0.2.1.dist-info/METADATA
convertext-0.2.1.dist-info/WHEEL
convertext-0.2.1.dist-info/entry_points.txt
convertext-0.2.1.dist-info/licenses/LICENSE
convertext-0.2.1.dist-info/RECORD
