Metadata-Version: 2.4
Name: convertext
Version: 0.2.1
Summary: Lightweight universal text/ebook/document format converter with CLI and API
License-Expression: MIT
License-File: LICENSE
Keywords: conversion,ebook,pdf,epub,mobi,docx,document
Author: danielcorsano
Requires-Python: >=3.9
Classifier: Development Status :: 3 - Alpha
Classifier: Intended Audience :: Developers
Classifier: Intended Audience :: End Users/Desktop
Classifier: Topic :: Text Processing :: Filters
Classifier: Topic :: Utilities
Classifier: Programming Language :: Python :: 3
Classifier: Programming Language :: Python :: 3.9
Classifier: Programming Language :: Python :: 3.10
Classifier: Programming Language :: Python :: 3.11
Classifier: Programming Language :: Python :: 3.12
Classifier: Programming Language :: Python :: 3.13
Requires-Dist: beautifulsoup4 (>=4.14.2)
Requires-Dist: click (>=8.1.0)
Requires-Dist: lxml (>=6.0.2)
Requires-Dist: markdown (>=3.9)
Requires-Dist: pillow (>=11.3.0)
Requires-Dist: pypdf (>=6.1.1)
Requires-Dist: python-docx (>=1.2.0)
Requires-Dist: pyyaml (>=6.0.3)
Requires-Dist: reportlab (>=4.0)
Requires-Dist: striprtf (>=0.0.26)
Project-URL: Homepage, https://github.com/danielcorsano/convertext
Project-URL: Repository, https://github.com/danielcorsano/convertext
